pydocless.py
pydocless-0.0.2.data/scripts/pydocless
pydocless-0.0.2.dist-info/LICENSE
pydocless-0.0.2.dist-info/METADATA
pydocless-0.0.2.dist-info/WHEEL
pydocless-0.0.2.dist-info/top_level.txt
pydocless-0.0.2.dist-info/RECORD
