Metadata-Version: 2.1
Name: pydocless
Version: 0.0.2
Summary: Python library for creating markdown documentation from python docstrings
Home-page: https://github.com/pentairiot/pydocless
Author: PentairIoT
Author-email: pentairiot@gmail.com
License: UNKNOWN
Platform: UNKNOWN
Classifier: Programming Language :: Python :: 3
Classifier: License :: OSI Approved :: MIT License
Classifier: Operating System :: OS Independent
